{"herb":"HuJISheng","names":{"pinyin":"hu ji sheng","hanzi":"槲寄生","latin":"herba visci","pharmaceuticalLatin":"Herba Visci","commonEnglish":["Colored Mistletoe"]},"category":"Herbs that Dispel Wind-Dampness","properties":{"taste":{"primary":["Bitter"],"secondary":[]},"temperature":{"primary":["Neutral"],"secondary":[]},"channels":{"primary":["Liver","Kidney"],"secondary":[]},"dose":{"general":"9-15g","other":[]}},"actions":{"sets":[{"action":{"primary":"Dispels Wind-Damp, tonifies the Liver and Kidneys, Strengthens the tendons and bones"},"indications":["Dizziness, rheumatoid arthritis, sores and weakness of waist and knees, weakness of tendons and bones."]},{"action":{"primary":"Prevents miscarriage"},"indications":["Metrorrhagia, metrostaxis, threatened abortion"]}]},"contra":{"contraindications":[],"incompatibilities":[],"interactions":[]},"combinations":{"sets":[]},"notes":["Hb. Visci Hu Ji Sheng is often used interchangeably with Hb. Taxilli #{SangJiSheng} Sang Ji Sheng. Both dispel Wind- Dampness, tonify the Liver and Kidneys, strengthen the tendons and bones and calm the fetus. Both are used for Wind-Damp Bi, lower back and leg pain and weakness, weakness of the sinews and bones and restless fetus patterns. However, Hu Ji Sheng is stronger at dispelling Wind-Dampness and is more often used for Bi Syndrome, while Sang Ji Sheng is stronger at tonifying the Liver and Kidneys and stabilizing the Chong and Ren channels.","Hu Ji Sheng is slightly toxic with side effects including general discomfort, nausea, vomiting, diffuse right hypochondriac pain, drowsiness, eye irritation, ataxia and seizures.","This herb is a parasite on a variety of deciduous trees."]}