{"herb":"LaoGuanCao","names":{"pinyin":"lao guan cao","hanzi":"老顴草","latin":"herba erodii seu geranii","pharmaceuticalLatin":"Herba Erodii/Geranii","commonEnglish":["Cranesbill","Common Heron's Bill Herb","Wilford Crane's Bill Herb"]},"category":"Herbs that Dispel Wind-Dampness","properties":{"taste":{"primary":["Acrid","Bitter"],"secondary":[]},"temperature":{"primary":["Neutral"],"secondary":["Slightly Warm"]},"channels":{"primary":["Liver","Kidney","Spleen","Large Intestine"],"secondary":[]},"dose":{"general":"9-30g","other":[]}},"actions":{"sets":[{"action":{"primary":"Dispels Wind, eliminates Dampness, invigorates the Blood and dredges and unblocks the channels and collaterals"},"indications":["Bi syndrome and other severe pain due to Wind-Dampness","Spasms and numbness"]},{"action":{"primary":"Clears Heat, resolves toxicity, stops diarrhea, generates flesh and stops itching"},"indications":["Sores, abscesses, burns and eczema","Dysenteric disorders"]}]},"contra":{"contraindications":[],"incompatibilities":[],"interactions":[]},"combinations":{"sets":[{"relatedHerbs":["XuDuan","WeiLingXian","ZhiCaoWu"],"useCases":["Painful obstruction due to Wind-Cold Dampness"]},{"relatedHerbs":["ShenJinCao","HanFangJi","DiLong"],"useCases":["Panarthralgia with swollen, enlarged and painful joints"]},{"relatedHerbs":["HuangBai","KuShen","DiFuZi"],"useCases":["Sores with significant exudate and pruritis"]},{"relatedHerbs":["HuangLian","MaChiXian"],"useCases":["Damp-Heat dysenteric disorders"]},{"relatedHerbs":["SangZhi","JiXueTeng","DangGui"],"useCases":["Bi syndrome"]},{"relatedHerbs":[],"useCases":["Diarrhea or dysentery"]}]},"notes":["This herb can be used alone for treating Bi syndrome.","It can be used alone for for infectious bowel disorders such as gastroenteritis and dysentery.","This herb has been shown to inhibit the growth of cancer cells.","It is said to dredge the channel to promote Blood circulation and free the collaterals.","For the treatment of injuries, arthralgia, numbness of the skin and paralysis, it is immersed in wine and taken frequently.","It was recorded that because it clears fever and detoxifies, it is good for carbuncles, cellulitis, sores and swelling."]}