{"herb":"LianFang","names":{"pinyin":"lian fang","hanzi":"莲房","latin":"nelumbinis receptaculum","pharmaceuticalLatin":"Nelumbinis Receptaculum Flos Nelumbinis","commonEnglish":["Lotus Seed Pot","Lotus Receptacle","Lotus Peduncle"]},"category":"Herbs that Regulate the Blood","properties":{"taste":{"primary":["Bitter","Astringent"],"secondary":[]},"temperature":{"primary":["Warm"],"secondary":[]},"channels":{"primary":["Liver","Spleen","Kidney"],"secondary":[]},"dose":{"general":"3-10g","tincture":"1-3ml","other":[]}},"actions":{"sets":[{"action":{"primary":"Stops bleeding and reduces Blood Stasis"},"indications":["Uterine bleeding and hematuria","Hemorrhoidal bleeding, rectal prolapse","Abdominal pain due to Blood Stagnation"]},{"action":{"primary":"Dispels Summerheat and Dampness"},"indications":["Diarrhea in children","Damp rashes, eczema"]}]},"contra":{"contraindications":[],"incompatibilities":[],"interactions":[]},"combinations":{"sets":[{"relatedHerbs":["YiMuCao"],"useCases":["Menorrhagia or metrorrhagia"]}]},"notes":["In its raw form, this herb removes Stasis but its ability to stop bleeding is slight and is used for retained placenta, hemorrhoids and prolonged lochia.","Use fresh to treat diarrhea in children from food poisoning.","Charred Lian Fang is the form most commonly used, especially for continuous uterine bleeding, hematuria, and bleeding hemorrhoids.","Because its effects are mild, it is used as an adjunctive herb.","Charred Lotus Receptacle Lian Fang Tan is better at restraining and inhibiting to stop bleeding."]}