{"herb":"XunGuFeng","names":{"pinyin":"xun gu feng","hanzi":"尋骨風","latin":"herba aristolochiae mollissimae","pharmaceuticalLatin":"Herba Aristolochiae Mollissimae","commonEnglish":["Mollissima","Hairy Birthwort"]},"category":"Obsolete Substances Herbs that Dispel Wind-Dampness","properties":{"taste":{"primary":["Bitter"],"secondary":[]},"temperature":{"primary":["Neutral","Slightly Toxic"],"secondary":[]},"channels":{"primary":["Liver"],"secondary":[]},"dose":{"general":"9-15g","other":[]}},"actions":{"sets":[{"action":{"primary":"Dispels Wind-Dampness, unblocks the channels and collaterals and stops pain"},"indications":["Wind-Damp Bi, numbness in the limbs, difficulty moving the joints and paralysis","General pain, including digestive and trauma induced","Toothache, malaria and abscess"]}]},"contra":{"contraindications":["Over dosage can led to nausea, vomiting, epigastric pain, anorexia, dizziness, headache, anxiety and a dry throat.","Contraindicated for those with Internal Heat due to Yin Deficiency."],"incompatibilities":[],"interactions":[]},"combinations":{"sets":[{"relatedHerbs":["WeiLingXian","ChuanXiong","FangFeng"],"useCases":["Wind-Damp Bi."]},{"relatedHerbs":["MuXiang","ShaRen","WuZhuYu"],"useCases":["Bloating and pain in the epigastrium with anorexia and acid regurgitation."]}]},"notes":["This herb can be used alone as a decoction or tincture for Wind-Dampness.","It can be used as a decoction or plaster for trauma.","This herb dissipates migratory pain.","This herb has been shown to inhibit the growth of cancer cells.","The whole plant is soaked in water and taken, for muscle, bone and Stomach pain.","It is also used to treat Damp-Heat.","It is primarily used for bone and Lung cancers."]}