{"formula":"LongHuWan","names":{"pinyin":"long hu wan","hanzi":"龙虎囊","english":"dragon and tiger pill","commonEnglish":"Dragon and Tiger Pill","aka":[""]},"herbs":[{"herb":"NiuHuang","dosage":"0.15-1g","actions":["Clears the Heart, opens the Orifices aromatically, awakens the Spirit, vaporizes Phlegm, clears the Liver and relieves Fire toxicity."]},{"herb":"BaDou","dosage":"0.1-0.3g","actions":["Warmly unblocks, vigorously purges, drives out water, reduces edema and breaks up clogged Phlegm.","With Zhu Sha and Niu Huang, for Phlegm Misting the Orifices."]},{"herb":"ZhuSha","dosage":"0.1-2.7g","actions":["Sedates the Heart, calms the Spirit, expels Phlegm, sedates jitteriness and clears Heat."]},{"herb":"MingFan","dosage":"0.6-1.5g","actions":["Clears Heat, purges Fire, relieves toxicity and expels Phlegm."]},{"herb":"GengMi","dosage":"9 to 15g","actions":["Tonifies the Qi of the Lungs, Spleen and Intestines, stops restlessness, stops thirst and generates fluids."]}],"actions":["Clears and sedates the Heart","Opens the Orifices","Calms the Shen","Clears Heat","Expels Phlegm"],"syndromes":["Liver Fire Generates Phlegm-Fire"],"manifestations":{"symptoms":["Acute onset","Irascibility","Headaches","A quick temper","Resorts to violence","Abusive language","Destruction of goods","Attacking people","Sudden tinnitus or","Sudden deafness","Flushed face","Red, swollen, painful eyes","Irascibility with violent angry outbursts","Dry mouth","Bitter taste in mouth","Thirst","Vomiting sour or bitter liquid","Insomnia","Restlessness","Constipation or dry stools","Maybe rib pain","In severe cases: Mania Hemoptysis Hematemesis Epistaxis"],"tongue":"Red tip and edges or Purplish","tongueCoat":"Thick, yellow, dry and rough","pulse":"Wiry, Excess and rapid"},"conditions":[{"condition":"Schizophrenia","name":"Schizophrenia"},{"name":""}],"contra":{"contraindications":["Use with extreme caution. Vomiting and diarrhea often occur after ingestion.","Use Cinnabaris Zhu Sha with extreme caution for those with compromised Liver and Kidney functions. Do not use it in large amounts or for a prolonged period."],"interactions":[""]},"notes":[""],"modifications":[]}