{"formula":"XieGanZhiYiWan","names":{"pinyin":"xie gan zhi yi wan","hanzi":"泻肝截遗丸","english":"drain the liver and stop emission pills","commonEnglish":"Drain the Liver and Stop Emission Pills","aka":[""]},"herbs":[{"herb":"LongDanCao","dosage":"6g","actions":["Drains Damp-Heat from the Liver and Gallbladder channels"]},{"herb":"ZhiZi","dosage":"12g","actions":["Drains Damp-Heat Cools and invigorates the Blood.","With Mu Dan Pi, resolves Qi Level Stagnation leading to Heat and Heat in the Blood."]},{"herb":"MuDanPi","dosage":"9g","actions":["Clears Heat, cools and harmonizes the Blood, invigorates the Blood, dispels Blood Stasis and Clears Liver Fire."]},{"herb":"ChaiHu","dosage":"9g","actions":["Spreads Liver Qi and relieves Stagnation.","With Long Dan Cao and Zhi Zi, for Excess Heat in the Liver and/or Gallbladder channels."]},{"herb":"ShengDiHuang","dosage":"9g","actions":["Clears Heat and cools the Blood."]},{"herb":"WuWeiZi","dosage":"9g","actions":["Tonifies the Kidneys, astringes Jing and stops diarrhea and spermatorrhea."]},{"herb":"MuLi","dosage":"20g","actions":["Calms the Liver, benefits Yin, anchors Floating Yang and prevents leakage of fluids."]}],"actions":["Clear Heat","Cools the Blood","Dispel Dampness","Regulates Qi"],"syndromes":["Damp-Heat in the Liver Channel"],"manifestations":{"symptoms":["Frequent spermatorrhea","Possible voiding of urine mixed with Jing","Possible itchy or Damp scrotum","Dry mouth","Bitter taste in the mouth","Voiding of dark-colored, turbid, hot urine","Itchy pain inside the penis","A bitter taste in the mouth","Flank pain","Damp, itchy genitals"],"tongue":"Red","tongueCoat":"Greasy and yellow","pulse":"Wiry"},"conditions":[{"condition":"Spermatorrhea","name":"Spermatorrhea"},{"name":""}],"contra":{"contraindications":[""],"interactions":[""]},"notes":[""],"modifications":[]}